inuits_module_loader/__init__.py
inuits_module_loader/module_loader.py
inuits_module_loader-1.0.3.dist-info/LICENSE
inuits_module_loader-1.0.3.dist-info/METADATA
inuits_module_loader-1.0.3.dist-info/WHEEL
inuits_module_loader-1.0.3.dist-info/top_level.txt
inuits_module_loader-1.0.3.dist-info/RECORD
